optimum/intel/nncf/__init__.py
optimum/intel/nncf/nncf_auto.py
optimum/intel/nncf/patches/modeling_utils.patch
optimum/intel/nncf/patches/trainer_4.11.0.patch
optimum/intel/nncf/patches/trainer_4.9.1.patch
optimum/intel/nncf/patches/trainer_callback.patch
optimum/intel/nncf/patches/training_args.patch
optimum/intel/openvino/__init__.py
optimum/intel/openvino/modeling_ov_auto.py
optimum/intel/openvino/modeling_ov_utils.py
optimum_openvino-0.0.2.dist-info/LICENSE
optimum_openvino-0.0.2.dist-info/METADATA
optimum_openvino-0.0.2.dist-info/WHEEL
optimum_openvino-0.0.2.dist-info/top_level.txt
optimum_openvino-0.0.2.dist-info/RECORD
