Metadata-Version: 2.1
Name: optimum-openvino
Version: 0.0.2
Summary: Intel OpenVINO extension for Hugging Face Transformers
Home-page: https://github.com/dkurt/optimum-openvino
Author: Intel Corporation
Author-email: openvino_pushbot@intel.com
License: Apache
Keywords: transformers,quantization,pruning,training,intel,openvino
Platform: UNKNOWN
Classifier: Development Status :: 3 - Alpha
Classifier: License :: OSI Approved :: Apache Software License
Classifier: Intended Audience :: Developers
Classifier: Intended Audience :: Education
Classifier: Intended Audience :: Science/Research
Classifier: Operating System :: OS Independent
Classifier: Programming Language :: Python :: 3
Classifier: Topic :: Scientific/Engineering :: Artificial Intelligence
License-File: LICENSE
Requires-Dist: transformers
Requires-Dist: openvino
Provides-Extra: all
Requires-Dist: openvino-dev[onnx] ; extra == 'all'
Requires-Dist: nncf ; extra == 'all'
Requires-Dist: transformers (<4.16.0) ; extra == 'all'
Provides-Extra: nncf
Requires-Dist: openvino-dev[onnx] ; extra == 'nncf'
Requires-Dist: nncf ; extra == 'nncf'
Requires-Dist: transformers (<4.16.0) ; extra == 'nncf'
